odoo/addons/l10n_fr_mis_reports/README.rst
odoo/addons/l10n_fr_mis_reports/__init__.py
odoo/addons/l10n_fr_mis_reports/__manifest__.py
odoo/addons/l10n_fr_mis_reports/data/mis_report_bs.xml
odoo/addons/l10n_fr_mis_reports/data/mis_report_bs_simplified.xml
odoo/addons/l10n_fr_mis_reports/data/mis_report_pl.xml
odoo/addons/l10n_fr_mis_reports/data/mis_report_pl_simplified.xml
odoo/addons/l10n_fr_mis_reports/data/mis_report_styles.xml
odoo/addons/l10n_fr_mis_reports/i18n/es.po
odoo/addons/l10n_fr_mis_reports/i18n/it.po
odoo/addons/l10n_fr_mis_reports/i18n/l10n_fr_mis_reports.pot
odoo/addons/l10n_fr_mis_reports/readme/CONFIGURE.md
odoo/addons/l10n_fr_mis_reports/readme/CONTRIBUTORS.md
odoo/addons/l10n_fr_mis_reports/readme/DESCRIPTION.md
odoo/addons/l10n_fr_mis_reports/readme/INSTALL.md
odoo/addons/l10n_fr_mis_reports/readme/USAGE.md
odoo/addons/l10n_fr_mis_reports/static/description/icon.png
odoo/addons/l10n_fr_mis_reports/static/description/index.html
odoo_addon_l10n_fr_mis_reports-18.0.1.0.0.3.dist-info/METADATA
odoo_addon_l10n_fr_mis_reports-18.0.1.0.0.3.dist-info/WHEEL
odoo_addon_l10n_fr_mis_reports-18.0.1.0.0.3.dist-info/top_level.txt
odoo_addon_l10n_fr_mis_reports-18.0.1.0.0.3.dist-info/RECORD
